torchok/__init__.py
torchok/example.py
torchok/tensor.py
torchok/autogradik/__init__.py
torchok/autogradik/functions.py
torchok/nn/__init__.py
torchok/nn/layers.py
torchok/nn/losses.py
torchok/nn/module.py
torchok/optim/__init__.py
torchok/optim/adam.py
torchok/optim/rmsprop.py
torchok/optim/sgd.py
torchoklib-1.0.1.dist-info/METADATA
torchoklib-1.0.1.dist-info/WHEEL
torchoklib-1.0.1.dist-info/top_level.txt
torchoklib-1.0.1.dist-info/RECORD
