Metadata-Version: 2.2
Name: torchoklib
Version: 1.0.1
Requires-Dist: numpy>=2.1.3
Dynamic: description
Dynamic: description-content-type
Dynamic: requires-dist
